{"cameraMode":{"drawMode":0,"name":"Shaded","section":"Shading Mode"},"sceneLighting":true,"audioPlay":false,"sceneViewState":{"showFog":true,"showMaterialUpdate":false,"showSkybox":true,"showFlares":true,"showImageEffects":true,"showParticleSystems":true},"in2DMode":false,"pivot":{"x":5.670843124389648,"y":5.742246627807617,"z":-34.840946197509769},"rotation":{"x":-0.0008641870226711035,"y":-0.7117658853530884,"z":0.7024471163749695,"w":-0.0008453598711639643},"size":79.8656234741211,"orthographic":false}